setup.py
jedhy/__init__.py
jedhy/api.hy
jedhy/inspection.hy
jedhy/macros.hy
jedhy/models.hy
jedhy.egg-info/PKG-INFO
jedhy.egg-info/SOURCES.txt
jedhy.egg-info/dependency_links.txt
jedhy.egg-info/requires.txt
jedhy.egg-info/top_level.txt
jedhy/__pycache__/__init__.cpython-37.pyc
jedhy/__pycache__/api.cpython-37.pyc
jedhy/__pycache__/inspection.cpython-37.pyc
jedhy/__pycache__/macros.cpython-37.pyc
jedhy/__pycache__/models.cpython-37.pyc